[{
        "pk": 1,
        "model": "store.musicproduct",
        "fields": {
            "sku": "pp5001340155",
            "name": "Digital Recorder",
            "description": "Mono Digital Voice Recorder with Built-In USB, 4 GB Memory, SD Memory Slot, 55 Hours Recording.",
            "has_sizes": "False",
            "price": 45.99,
            "category": 1,
            "rating": 4.6,
            "image_url": "https://belle-musique-studio.s3.eu-west-2.amazonaws.com/media/digital-recorder.jpg",
            "image": "digital-recorder.jpg",
            "image_alt": "A portable sound recording device."
        }
    }, {
        "pk": 2,
        "model": "store.musicproduct",
        "fields": {
            "sku": "pp5001600425",
            "name": "RockJam Electronic Keyboard",
            "description": "The RockJam 661 keyboard piano super kit includes an electronic keyboard with 61 full-size keys that provides you with a traditional piano feel whilst maintaining a portable and compact design that can be powered by either mains power (power supply included) or batteries.",
            "has_sizes": "False",
            "price": 97.99,
            "category": 2,
            "rating": 4.8,
            "image_url": "https://belle-musique-studio.s3.eu-west-2.amazonaws.com/media/keyboard.jpg",
            "image": "keyboard.jpg",
            "image_alt": "A large electric piano keyboard."
        }
    }, {
        "pk": 3,
        "model": "store.musicproduct",
        "fields": {
            "sku": "pp5001730010",
            "name": "Ricola Soothe and Clear Lozenges",
            "description": "Ricola Soothe and Clear Honey Lemon and Echinacea Bag, Naturally Soothing Throat Lozenges, 75 g Pack of 12 Bags",
            "has_sizes": "False",
            "price": 18.99,
            "category": 1,
            "rating": 4.7,
            "image_url": "https://belle-musique-studio.s3.eu-west-2.amazonaws.com/media/lozenges.jpg",
            "image": "lozenges.jpg",
            "image_alt": "Orange throat lozenges. "
        }
    }, {
        "pk": 4,
        "model": "store.musicproduct",
        "fields": {
            "sku": "pp5001890157",
            "name": "Professional LPK25 MIDI Keyboard",
            "description": "Professional LPK25 - Portable USB-powered MIDI Keyboard with 25 Velocity-Sensitive Keys with Synth Action for Laptops (Mac & PC), Editing Software Included.",
            "has_sizes": "False",
            "price": 38.99,
            "category": 2,
            "rating": 4.25,
            "image_url": "https://belle-musique-studio.s3.eu-west-2.amazonaws.com/media/mini-keyboard.JPG",
            "image": "mini-keyboard.JPG",
            "image_alt": "A small electric piano keyboard."
        }
    }, {
        "pk": 5,
        "model": "store.musicproduct",
        "fields": {
            "sku": "pp5002111605",
            "name": "Digital Metronome - White & Silver",
            "description": "Multi-function compact metronome. Enhanced display makes it easier to practice your rhythm and phrasing. Choose from two types of tempo steps: pendulum steps or full steps. Up to approximately 290 hours of continuous operation.",
            "has_sizes": "False",
            "price": 25.99,
            "category": 1,
            "rating": 5.0,
            "image_url": "https://belle-musique-studio.s3.eu-west-2.amazonaws.com/media/metronome.jpg",
            "image": "metronome.jpg",
            "image_alt": "A metronome used to keep time."
        }
    }, {
        "pk": 6,
        "model": "store.musicproduct",
        "fields": {
            "sku": "pp5002260206",
            "name": "Shure Vocal Microphone",
            "description": "Shure SM58-LCE Cardioid Dynamic Vocal Microphone with Pneumatic Shock Mount, Spherical Mesh Grille with Built-in Pop Filter, A25D Mic Clip, Storage Bag, 3-pin XLR Connector - (No Cable Included)",
            "has_sizes": "False",
            "price": 86.99,
            "category": 2,
            "rating": 5.0,
            "image_url": "https://belle-musique-studio.s3.eu-west-2.amazonaws.com/media/microphone.jpg",
            "image": "microphone.jpg",
            "image_alt": "A microphone to sing into."
        }
    }, {
        "pk": 7,
        "model": "store.musicproduct",
        "fields": {
            "sku": "pp5002440521",
            "name": "Blank Sheet Music",
            "description": "Blank Sheet Music, 12 stave staff paper, 100 pages, A4 8.5x11 inch Music Manuscript Paper Musicians Notebook for composing music & writing music notation",
            "has_sizes": "False",
            "price": 4.50,
            "category": 1,
            "rating": 4.4,
            "image_url": "https://belle-musique-studio.s3.eu-west-2.amazonaws.com/media/music-sheets.jpg",
            "image": "music-sheets.jpg",
            "image_alt": "Plain white music sheets with music bars to write your own music."
        }
    }, {
        "pk": 8,
        "model": "store.musicproduct",
        "fields": {
            "sku": "pp5002601115",
            "name": "Windsor Music Stand",
            "description": "Windsor 050151-BK Adjustable Folding Sheet Music Stand with Carry Case Black. Constructed of steel this music stand is made to be both portable music stand and comes with a travel bag to help you transport for performances or lessons.",
            "has_sizes": "False",
            "price": 14.99,
            "category": 1,
            "rating": 4.5,
            "image_url": "https://belle-musique-studio.s3.eu-west-2.amazonaws.com/media/music-stand.jpg",
            "image": "music-stand.jpg",
            "image_alt": "A black metal stand used to hold music sheets."
        }
    }, {
        "pk": 9,
        "model": "store.musicproduct",
        "fields": {
            "sku": "pp5002690715",
            "name": "Music Theory: From Beginner to Expert",
            "description": "Music Theory: From Beginner to Expert - The Ultimate Step-By-Step Guide to Understanding and Learning Music Theory Effortlessly: 1 (Essential Learning Tools for Musicians) ",
            "has_sizes": "False",
            "price": 16.99,
            "category": 1,
            "rating": 4.7,
            "image_url": "https://belle-musique-studio.s3.eu-west-2.amazonaws.com/media/music-theory-book.jpg",
            "image": "music-theory-book.jpg",
            "image_alt": "A book of music theory lessons."
        }
    }, {
        "pk": 10,
        "model": "store.musicproduct",
        "fields": {
            "sku": "pp5002701115",
            "name": "30 Piano Sheet Music for Beginners",
            "description": "Famous & Easy Pieces of Classical & Folk Music, Organized from the Easiest to the most Difficult!",
            "has_sizes": "False",
            "price": 9.99,
            "category": 1,
            "rating": 4.4,
            "image_url": "https://belle-musique-studio.s3.eu-west-2.amazonaws.com/media/piano-music.jpg",
            "image": "piano-music.jpg",
            "image_alt": "A picture of piano sheet music."
        }
    }, {
        "pk": 11,
        "model": "store.musicproduct",
        "fields": {
            "sku": "pp5002761055",
            "name": "Sound Recording Equipment",
            "description": "Audio Interface with DJ Mixer Sound Card, Portable Podcast Equipment Bundle XLR to 3.5mm Microphone Studio Board Voice Changer for youtube/tiktok PC/Phone Live Streaming/Recording/Gaming",
            "has_sizes": "False",
            "price": 109.99,
            "category": 2,
            "rating": 4.0,
            "image_url": "https://belle-musique-studio.s3.eu-west-2.amazonaws.com/media/sound-equipment.jpg",
            "image": "sound-equipment.jpg",
            "image_alt": "A picture of sound recording equipment"
        }
    },
    {
        "pk": 12,
        "model": "store.musicproduct",
        "fields": {
            "sku": "pp5002761056",
            "name": "I Love Music T-Shirt",
            "description": "A fantastic pure cotton t-shirt available in multiple sizes. A must have for a music lover's wardrobe!",
            "has_sizes": "True",
            "price": 17.99,
            "category": 1,
            "rating": 4.8,
            "image_url": "https://belle-musique-studio.s3.eu-west-2.amazonaws.com/media/love-music-tshirt.jpg",
            "image": "love-music-tshirt.jpg",
            "image_alt": "A grey t-shirt which states I Love Music."
        }
    }
]